midscene/__init__.py
midscene/android/__init__.py
midscene/android/agent.py
midscene/android/device.py
midscene/cli/__init__.py
midscene/cli/config.py
midscene/cli/main.py
midscene/core/__init__.py
midscene/core/agent.py
midscene/core/insight.py
midscene/core/types.py
midscene/core/ai_model/__init__.py
midscene/core/ai_model/providers.py
midscene/core/ai_model/service.py
midscene/shared/__init__.py
midscene/shared/cache.py
midscene/shared/logger.py
midscene/shared/report.py
midscene/web/__init__.py
midscene/web/bridge.py
midscene/web/playwright_page.py
midscene/web/selenium_page.py
midscene_python-0.1.1.dist-info/METADATA
midscene_python-0.1.1.dist-info/WHEEL
midscene_python-0.1.1.dist-info/entry_points.txt
midscene_python-0.1.1.dist-info/licenses/LICENSE
midscene_python-0.1.1.dist-info/RECORD
