Metadata-Version: 2.4
Name: midscene-python
Version: 0.1.1
Summary: 基于AI的Web和Android自动化框架，支持自然语言驱动的UI操作
Project-URL: Homepage, https://github.com/Python51888/midscene-python.git
Project-URL: Repository, https://github.com/Python51888/midscene-python.git
Project-URL: Documentation, https://github.com/Python51888/Midscene-Python/blob/master/README.md
Project-URL: Bug Tracker, https://github.com/Python51888/midscene-python.git/issues
Author: Midscene Team
License-Expression: MIT
License-File: LICENSE
Keywords: AI,android,automation,playwright,selenium,testing,ui,web
Classifier: Development Status :: 4 - Beta
Classifier: Intended Audience :: Developers
Classifier: License :: OSI Approved :: MIT License
Classifier: Programming Language :: Python :: 3
Classifier: Programming Language :: Python :: 3.9
Classifier: Programming Language :: Python :: 3.10
Classifier: Programming Language :: Python :: 3.11
Classifier: Programming Language :: Python :: 3.12
Classifier: Topic :: Software Development :: Libraries :: Python Modules
Classifier: Topic :: Software Development :: Testing
Requires-Python: >=3.9
Requires-Dist: aiohttp<4.0,>=3.9.0
Requires-Dist: anthropic<1.0,>=0.7.0
Requires-Dist: asyncio-mqtt
Requires-Dist: dashscope
Requires-Dist: google-generativeai
Requires-Dist: httpx<1.0,>=0.25.0
Requires-Dist: jinja2<4.0,>=3.1.0
Requires-Dist: loguru<1.0,>=0.7.0
Requires-Dist: numpy<2.0,>=1.24.0
Requires-Dist: openai<2.0,>=1.3.0
Requires-Dist: opencv-python<5.0,>=4.8.0
Requires-Dist: pillow<11.0,>=10.0.0
Requires-Dist: playwright<2.0,>=1.40.0
Requires-Dist: pure-python-adb>=0.3.0dev0
Requires-Dist: pydantic<3.0,>=2.0
Requires-Dist: pyyaml<7.0,>=6.0
Requires-Dist: selenium<5.0,>=4.15.0
Requires-Dist: typer<1.0,>=0.9.0
Provides-Extra: dev
Requires-Dist: black>=23.0.0; extra == 'dev'
Requires-Dist: isort>=5.12.0; extra == 'dev'
Requires-Dist: mypy>=1.5.0; extra == 'dev'
Requires-Dist: pre-commit>=3.4.0; extra == 'dev'
Requires-Dist: pytest-asyncio>=0.21.0; extra == 'dev'
Requires-Dist: pytest-cov>=4.1.0; extra == 'dev'
Requires-Dist: pytest>=7.4.0; extra == 'dev'
Requires-Dist: ruff>=0.1.0; extra == 'dev'
Provides-Extra: docs
Requires-Dist: mkdocs-material>=9.4.0; extra == 'docs'
Requires-Dist: mkdocs>=1.5.0; extra == 'docs'
Requires-Dist: mkdocstrings[python]>=0.23.0; extra == 'docs'
